README.rst
setup.py
animatai/LICENSE
animatai/__init__.py
animatai/agents.py
animatai/config.py.template
animatai/history.py
animatai/index.html
animatai/mdp.py
animatai/network.py
animatai/network_rl.py
animatai/start.sh
animatai/utils.py
animatai/wsserver.py
animatai.egg-info/PKG-INFO
animatai.egg-info/SOURCES.txt
animatai.egg-info/dependency_links.txt
animatai.egg-info/requires.txt
animatai.egg-info/top_level.txt
animatai/images/terrain.png
test/test_agents.py
test/test_history.py
test/test_mdp.py
test/test_network.py
test/test_network_rl.py