Metadata-Version: 1.1
Name: animatai
Version: 0.1.4
Summary: Ecosystem with animats for development of Artificial General Intelligence
Home-page: https://github.com/animatai/animatai
Author: Jonas Colmsjö
Author-email: jonas.colmsjo@gizur.com
License: MIT
Keywords: animat ai agi artificial intelligence
Platform: UNKNOWN
Classifier: Development Status :: 3 - Alpha
Classifier: Intended Audience :: Developers
Classifier: Topic :: Software Development :: Libraries :: Python Modules
Classifier: License :: OSI Approved :: MIT License
Classifier: Programming Language :: Python :: 3
